setup.py
cpf_cnpj/__init__.py
cpf_cnpj/cpf_cnpj.py
cpf_cnpj.egg-info/PKG-INFO
cpf_cnpj.egg-info/SOURCES.txt
cpf_cnpj.egg-info/dependency_links.txt
cpf_cnpj.egg-info/top_level.txt
cpf_cnpj.egg-info/zip-safe
cpf_cnpj/tests/__init__.py
cpf_cnpj/tests/tests.py