Metadata-Version: 1.0
Name: cpf-cnpj
Version: 0.1.4
Summary: Validador de CPF e CNPJ para Python
Home-page: https://github.com/amargarin/cpf_cnpj
Author: Adriano Margarin
Author-email: adriano.margarin@gmail.com
License: MIT
Keywords: python cpf cnpj validador
Platform: UNKNOWN
